pylasr.cpython-311-x86_64-linux-gnu.so
pylasr.libs/libLerc-72b478d0.so.4
pylasr.libs/libarchive-0fe2a86b.so.13.8.1
pylasr.libs/libblosc-68e87add.so.1.21.6
pylasr.libs/libbz2-cf126ca7.so.1.0.8
pylasr.libs/libcharset-ec0a1feb.so.1.0.0
pylasr.libs/libcom_err-08b34f69.so.3.0
pylasr.libs/libcrypto-d961dd36.so.3
pylasr.libs/libcurl-64ca73ad.so.4.8.0
pylasr.libs/libdeflate-577b71e3.so.0
pylasr.libs/libfreexl-c4b2df32.so.1.2.0
pylasr.libs/libgdal-9bb14d5a.so.36.3.10.3
pylasr.libs/libgeos-5464ceeb.so.3.14.0
pylasr.libs/libgeos_c-745e8663.so.1.20.4
pylasr.libs/libgeotiff-75fe9221.so.5.2.4
pylasr.libs/libgif-179299f2.so.7.2.0
pylasr.libs/libgssapi_krb5-4c656fbe.so.2.2
pylasr.libs/libiconv-ec9f94ed.so.2.7.0
pylasr.libs/libicudata-e065d9cb.so.75.1
pylasr.libs/libicui18n-8332a1c6.so.75.1
pylasr.libs/libicuuc-c9a25b32.so.75.1
pylasr.libs/libjpeg-c09c12ee.so.8.3.2
pylasr.libs/libjson-c-b891e052.so.5.4.0
pylasr.libs/libk5crypto-ddd2f581.so.3.1
pylasr.libs/libkeyutils-cdae6f9f.so.1.10
pylasr.libs/libkmlbase-0da1e84c.so.1.3.0
pylasr.libs/libkmldom-63451fb7.so.1.3.0
pylasr.libs/libkmlengine-f8058332.so.1.3.0
pylasr.libs/libkrb5-e96d72a4.so.3.3
pylasr.libs/libkrb5support-41cbade6.so.0.1
pylasr.libs/liblz4-34f4953d.so.1.10.0
pylasr.libs/liblzma-99dbefdd.so.5
pylasr.libs/liblzo2-7fb098cc.so.2.0.0
pylasr.libs/libminizip-3c51c87c.so.4.0.10
pylasr.libs/libnghttp2-1428bd5c.so.14.29.0
pylasr.libs/libnsl-61d409bf.so.3.0.0
pylasr.libs/libpcre2-8-8dde3c05.so.0.14.0
pylasr.libs/libpng16-bd65464e.so.16.50.0
pylasr.libs/libproj-a180ae43.so.25.9.6.2
pylasr.libs/librttopo-ae154a20.so.1.1.0
pylasr.libs/libsharpyuv-4ca18185.so.0.1.2
pylasr.libs/libsnappy-6bf1521f.so.1.2.2
pylasr.libs/libspatialite-21aa6048.so.8.1.0
pylasr.libs/libsqlite3-df054c7d.so.3.50.4
pylasr.libs/libssh2-00a44912.so.1.0.1
pylasr.libs/libssl-f70ed0ac.so.3
pylasr.libs/libtiff-16893e2e.so.6.2.0
pylasr.libs/liburiparser-0bf6d6c7.so.1.0.31
pylasr.libs/libwebp-d97406a1.so.7.2.0
pylasr-0.17.2.dist-info/METADATA
pylasr-0.17.2.dist-info/WHEEL
pylasr-0.17.2.dist-info/top_level.txt
pylasr-0.17.2.dist-info/RECORD
