Metadata-Version: 2.4
Name: pylasr
Version: 0.17.2
Summary: Python bindings for LASR library - Fast Airborne LiDAR Data Processing
Author-email: Jean-Romain Roussel <info@r-lidar.com>, Alexey Grigoryev <agrigoriev@gmail.com>, Kirill Semenov <ksemchh@gmail.com>
License: GPL-3.0
Project-URL: Homepage, https://github.com/r-lidar/lasR
Project-URL: Bug Tracker, https://github.com/r-lidar/lasR/issues
Project-URL: Documentation, https://r-lidar.github.io/lasR/
Project-URL: Source Code, https://github.com/r-lidar/lasR
Keywords: lidar,point cloud,gis,remote sensing,airborne laser scanning
Classifier: Development Status :: 4 - Beta
Classifier: Intended Audience :: Developers
Classifier: Intended Audience :: Science/Research
Classifier: Operating System :: OS Independent
Classifier: Programming Language :: Python :: 3
Classifier: Programming Language :: Python :: 3.9
Classifier: Programming Language :: Python :: 3.10
Classifier: Programming Language :: Python :: 3.11
Classifier: Programming Language :: Python :: 3.12
Classifier: Programming Language :: Python :: 3.13
Classifier: Topic :: Scientific/Engineering :: GIS
Classifier: Topic :: Software Development :: Libraries :: Python Modules
Requires-Python: >=3.9
